setup.cfg
setup.py
mclient/__init__.py
mclient/mclient.py
mclient.egg-info/PKG-INFO
mclient.egg-info/SOURCES.txt
mclient.egg-info/dependency_links.txt
mclient.egg-info/entry_points.txt
mclient.egg-info/requires.txt
mclient.egg-info/top_level.txt