Metadata-Version: 1.1
Name: mclient
Version: 0.1.4
Summary: CLI and Client library for Mirage external service virtualization
Home-page: https://github.com/rusenask/mirage-client
Author: Karolis Rusenas
Author-email: karolis.rusenas@gmail.com
License: GPLv3
Keywords: testing,cli,mirage,client
Platform: UNKNOWN
Requires: docopt
Requires: requests
Requires: PyYAML
